{"MIN win_percentage_for_player_X":0.0,"r2c3":"X","r3c2":"_","r3c3":"O","Grid":"X,O,X\nO,_,X\nX,_,O","BEST child X":8,"WORST child tie":8,"children":{"86d3a84a1ee3fd0987dfd34753390afda497ca69f688ad1d3eee5054487a6f35":{"win_percentage_for_player_O":0.0,"tie_percentage":100.0,"Priority":false,"Randomly chosen grid location":5,"win_percentage_for_player_X":0.0},"9d69c1e662efbee43d46d8cfd800a00c6e25d8c94f5000c9bf7a97469a92c104":{"win_percentage_for_player_O":0.0,"tie_percentage":0.0,"Priority":false,"Randomly chosen grid location":8,"win_percentage_for_player_X":100.0}},"tie_percentage":50.0,"MAX tie_percentage":100.0,"r1c1":"X","r1c2":"O","r2c1":"O","BEST child O":0,"r1c3":"X","r2c2":"_","r3c1":"X","BEST child tie":5,"win_percentage_for_player_O":0.0,"Randomly chosen grid location":3,"MAX win_percentage_for_player_X":100.0,"WORST child X":5,"Children Amount":2,"MAX win_percentage_for_player_O":0.0,"stateOccurenceCounter":13,"MIN tie_percentage":0.0,"win_percentage_for_player_X":50.0,"WORST child O":5,"MIN win_percentage_for_player_O":0.0}