{"MIN win_percentage_for_player_X":10.0,"r2c3":"_","r3c2":"O","r3c3":"X","Grid":"X,O,_\nO,_,_\nX,O,X","BEST child X":5,"WORST child tie":3,"children":{"49b61673747113bc2d416254a95473b065bd8b0e9131c5d7438e54834c6b45aa":{"win_percentage_for_player_O":50.0,"tie_percentage":0.0,"Priority":false,"Randomly chosen grid location":3,"win_percentage_for_player_X":50.0},"e9f22b410fdc9b34d84f1fc3c9ff58545eaff4afd80e8f01694bf79e077020f5":{"win_percentage_for_player_O":0.0,"tie_percentage":0.0,"Priority":false,"Randomly chosen grid location":5,"win_percentage_for_player_X":100.0}},"tie_percentage":0.0,"MAX tie_percentage":0.0,"r1c1":"X","r1c2":"O","r2c1":"O","BEST child O":3,"r1c3":"_","r2c2":"_","r3c1":"X","BEST child tie":0,"win_percentage_for_player_O":25.0,"Randomly chosen grid location":2,"MAX win_percentage_for_player_X":100.0,"WORST child X":0,"Children Amount":2,"MAX win_percentage_for_player_O":50.0,"stateOccurenceCounter":6,"MIN tie_percentage":0.0,"win_percentage_for_player_X":75.0,"WORST child O":5,"MIN win_percentage_for_player_O":0.0}