{"MIN win_percentage_for_player_X":0.0,"r2c3":"X","r3c2":"O","r3c3":"_","Grid":"_,X,_\nO,_,X\nX,O,_","BEST child X":1,"WORST child tie":0,"children":{"b022741458d3be7e5a58057b078d7b8e7c789d47d74e3e14ecbaa05f862b41e4":{"win_percentage_for_player_O":0.0,"tie_percentage":100.0,"Priority":false,"Randomly chosen grid location":3,"win_percentage_for_player_X":0.0},"ff3e3c430f88312cd608d9cca83d9adbfd5bc327b2a0bdf2262eef07b90da726":{"win_percentage_for_player_O":0.0,"tie_percentage":33.333333333333336,"Priority":false,"Randomly chosen grid location":9,"win_percentage_for_player_X":66.66666666666667},"534b98f91bae9b8583cc50cacc19a9774a866b6929ccb557e3e481bd90ee765f":{"win_percentage_for_player_O":0.0,"tie_percentage":25.0,"Priority":false,"Randomly chosen grid location":1,"win_percentage_for_player_X":75.0}},"tie_percentage":52.77777777777778,"MAX tie_percentage":100.0,"r1c1":"_","r1c2":"X","r2c1":"O","BEST child O":0,"r1c3":"_","r2c2":"_","r3c1":"X","BEST child tie":3,"win_percentage_for_player_O":0.0,"Randomly chosen grid location":6,"MAX win_percentage_for_player_X":75.0,"WORST child X":3,"Children Amount":3,"MAX win_percentage_for_player_O":0.0,"stateOccurenceCounter":10,"MIN tie_percentage":10.0,"win_percentage_for_player_X":47.22222222222223,"WORST child O":3,"MIN win_percentage_for_player_O":0.0}