{"MIN win_percentage_for_player_X":10.0,"r2c3":"O","r3c2":"_","r3c3":"O","Grid":"_,X,_\n_,_,O\nX,_,O","BEST child X":5,"WORST child tie":8,"children":{"2e27dcff949c0c9228db9fa11e9d957d3c00ad92d5690e320f973f56e9364222":{"win_percentage_for_player_O":72.22222222222223,"tie_percentage":0.0,"Priority":false,"Randomly chosen grid location":8,"win_percentage_for_player_X":16.666666666666668},"733dcd0c4aaec84a1117bcde0fd32f1e8e69d67cdcee1fe679e0d066188ba9a0":{"win_percentage_for_player_O":12.5,"tie_percentage":0.0,"Priority":false,"Randomly chosen grid location":4,"win_percentage_for_player_X":37.5},"27469be44f8ae4076db81ddd3a46358755acd220531fc2af084f414564d969a1":{"win_percentage_for_player_O":37.5,"tie_percentage":0.0,"Priority":false,"Randomly chosen grid location":5,"win_percentage_for_player_X":58.33333333333334},"65f4bbaa57b2a4dec86d2b03d5d43d194fe04a87ead0b46aa1da902c232d38c4":{"win_percentage_for_player_O":37.5,"tie_percentage":0.0,"Priority":false,"Randomly chosen grid location":1,"win_percentage_for_player_X":45.833333333333336},"3793f275897a03a470f6ec3d3d73348f2fc03f5d98eb77f530d756fb36cf83e8":{"win_percentage_for_player_O":25.000000000000004,"tie_percentage":0.0,"Priority":false,"Randomly chosen grid location":3,"win_percentage_for_player_X":50.0}},"tie_percentage":0.0,"MAX tie_percentage":0.0,"r1c1":"_","r1c2":"X","r2c1":"_","BEST child O":8,"r1c3":"_","r2c2":"_","r3c1":"X","BEST child tie":0,"win_percentage_for_player_O":36.94444444444444,"Randomly chosen grid location":6,"MAX win_percentage_for_player_X":58.33333333333334,"WORST child X":0,"Children Amount":5,"MAX win_percentage_for_player_O":72.22222222222223,"stateOccurenceCounter":27,"MIN tie_percentage":0.0,"win_percentage_for_player_X":41.66666666666667,"WORST child O":0,"MIN win_percentage_for_player_O":10.0}