{"MIN win_percentage_for_player_X":5.555555555555556,"r2c3":"_","r3c2":"X","r3c3":"_","Grid":"_,_,_\nO,O,_\nX,X,_","BEST child X":3,"WORST child tie":9,"children":{"f661dc1af6d44f4177d3433d2077d2cac898251164065f1ab949a5bd845739f9":{"win_percentage_for_player_O":35.41666666666667,"tie_percentage":29.166666666666668,"Priority":false,"Randomly chosen grid location":1,"win_percentage_for_player_X":35.41666666666667},"cc532f8cb1d88b1e84a4ba1bc5e4086b3f718b6e295165f379e500729aec1d6b":{"win_percentage_for_player_O":1.4980776123852632E307,"tie_percentage":1.4980776123852632E307,"Priority":false,"Randomly chosen grid location":3,"win_percentage_for_player_X":1.4980776123852632E307},"e3384791c4d97787eb3352439cb01c8062d479686f210dd886526a4d4b7e2cd":{"win_percentage_for_player_O":55.555555555555564,"tie_percentage":27.777777777777782,"Priority":false,"Randomly chosen grid location":2,"win_percentage_for_player_X":5.555555555555556},"3e4a9bf249e676fbf5d8c75bb8f087537ed5c10cdbbc7a411881898e3cfd6a4d":{"win_percentage_for_player_O":1.4980776123852632E307,"tie_percentage":1.4980776123852632E307,"Priority":false,"Randomly chosen grid location":6,"win_percentage_for_player_X":1.4980776123852632E307},"3376cff6bdb504956d21332ea9f1e694e95cdb57f91a6c66e1e093febe1ce1f4":{"win_percentage_for_player_O":0.0,"tie_percentage":0.0,"Priority":false,"Randomly chosen grid location":9,"win_percentage_for_player_X":100.0}},"tie_percentage":5.992310449541053E306,"MAX tie_percentage":1.4980776123852632E307,"r1c1":"_","r1c2":"_","r2c1":"O","BEST child O":3,"r1c3":"_","r2c2":"O","r3c1":"X","BEST child tie":3,"win_percentage_for_player_O":5.992310449541053E306,"Randomly chosen grid location":4,"MAX win_percentage_for_player_X":1.4980776123852632E307,"WORST child X":2,"Children Amount":5,"MAX win_percentage_for_player_O":1.4980776123852632E307,"stateOccurenceCounter":13,"MIN tie_percentage":0.0,"win_percentage_for_player_X":5.992310449541053E306,"WORST child O":9,"MIN win_percentage_for_player_O":0.0}