{"MIN win_percentage_for_player_X":10.0,"r2c3":"O","r3c2":"_","r3c3":"O","Grid":"X,_,X\nX,O,O\n_,_,O","BEST child X":7,"WORST child tie":7,"children":{"ded0eee0bdba0d8f0b709f9667eada19c177cbe2578966fa23f01f38ee0d39f7":{"win_percentage_for_player_O":0.0,"tie_percentage":0.0,"Priority":false,"Randomly chosen grid location":7,"win_percentage_for_player_X":100.0},"29ebc36320df8b19ba9efb6cefca02eb47e3e528bfdfe1cf2ec6f98a6946d6da":{"win_percentage_for_player_O":0.0,"tie_percentage":0.0,"Priority":false,"Randomly chosen grid location":2,"win_percentage_for_player_X":100.0},"a661b3d51e88f2fe88a228843231b4bf6c2c96039384284c6f32b114afbfebd9":{"win_percentage_for_player_O":0.0,"tie_percentage":0.0,"Priority":false,"Randomly chosen grid location":8,"win_percentage_for_player_X":100.0}},"tie_percentage":0.0,"MAX tie_percentage":0.0,"r1c1":"X","r1c2":"_","r2c1":"X","BEST child O":0,"r1c3":"X","r2c2":"O","r3c1":"_","BEST child tie":0,"win_percentage_for_player_O":0.0,"Randomly chosen grid location":9,"MAX win_percentage_for_player_X":100.0,"WORST child X":0,"Children Amount":3,"MAX win_percentage_for_player_O":0.0,"stateOccurenceCounter":12,"MIN tie_percentage":0.0,"win_percentage_for_player_X":100.0,"WORST child O":7,"MIN win_percentage_for_player_O":0.0}