{"MIN win_percentage_for_player_X":10.0,"r2c3":"_","r3c2":"_","r3c3":"X","Grid":"X,O,_\nO,_,_\nX,_,X","BEST child X":5,"WORST child tie":5,"children":{"a183dbe3c9b201bc8699e70df252537cc52f855fd06e9920c1d4c57846661153":{"win_percentage_for_player_O":75.0,"tie_percentage":0.0,"Priority":false,"Randomly chosen grid location":5,"win_percentage_for_player_X":25.0}},"tie_percentage":0.0,"MAX tie_percentage":0.0,"r1c1":"X","r1c2":"O","r2c1":"O","BEST child O":5,"r1c3":"_","r2c2":"_","r3c1":"X","BEST child tie":0,"win_percentage_for_player_O":75.0,"Randomly chosen grid location":9,"MAX win_percentage_for_player_X":25.0,"WORST child X":0,"Children Amount":1,"MAX win_percentage_for_player_O":75.0,"stateOccurenceCounter":2,"MIN tie_percentage":0.0,"win_percentage_for_player_X":25.0,"WORST child O":0,"MIN win_percentage_for_player_O":10.0}