{"MIN win_percentage_for_player_X":10.0,"r2c3":"O","r3c2":"_","r3c3":"X","Grid":"X,_,O\n_,_,O\nX,_,X","BEST child X":8,"WORST child tie":5,"children":{"dc13506ff856d3180509ae448a41db232f6b3d7dc15ee55c3e23aeab8eba4b4e":{"win_percentage_for_player_O":16.666666666666668,"tie_percentage":0.0,"Priority":false,"Randomly chosen grid location":5,"win_percentage_for_player_X":83.33333333333333},"5ceae6004f9768b1929441865df5e38304d200650198dbef291dc2b3735c9ad2":{"win_percentage_for_player_O":0.0,"tie_percentage":0.0,"Priority":false,"Randomly chosen grid location":4,"win_percentage_for_player_X":50.0},"35bf3b3e9a06e42c7376d11e1313bd78be1c3e94bb3e54ec4a064f7020abec89":{"win_percentage_for_player_O":0.0,"tie_percentage":0.0,"Priority":false,"Randomly chosen grid location":8,"win_percentage_for_player_X":100.0},"d8c1823f544ef7d79042e614c095f2676537a1bac63d3ce912529874f1cd3936":{"win_percentage_for_player_O":0.0,"tie_percentage":0.0,"Priority":false,"Randomly chosen grid location":2,"win_percentage_for_player_X":66.66666666666667}},"tie_percentage":0.0,"MAX tie_percentage":0.0,"r1c1":"X","r1c2":"_","r2c1":"_","BEST child O":5,"r1c3":"O","r2c2":"_","r3c1":"X","BEST child tie":0,"win_percentage_for_player_O":4.166666666666667,"Randomly chosen grid location":9,"MAX win_percentage_for_player_X":100.0,"WORST child X":0,"Children Amount":4,"MAX win_percentage_for_player_O":16.666666666666668,"stateOccurenceCounter":12,"MIN tie_percentage":0.0,"win_percentage_for_player_X":75.0,"WORST child O":4,"MIN win_percentage_for_player_O":0.0}