{"MIN win_percentage_for_player_X":10.0,"r2c3":"_","r3c2":"_","r3c3":"X","Grid":"_,_,_\nO,X,_\nO,_,X","BEST child X":8,"WORST child tie":8,"children":{"ca34b570db7aaa2aed28bb18233edfa399e186266cd580d0956089924a71ca74":{"Priority":true,"Randomly chosen grid location":8},"16cf833fd700233f8551543c35d18748b8ef3103e0075c94fb223aee5deebd3":{"win_percentage_for_player_O":0.0,"tie_percentage":0.0,"Priority":false,"Randomly chosen grid location":1,"win_percentage_for_player_X":100.0},"2ed053c1a8724c51c2035ebfc1e7866390e127e49f580ed12f09f197fa2662b2":{"win_percentage_for_player_O":1.7976931348623157E308,"tie_percentage":1.7976931348623157E308,"Priority":false,"Randomly chosen grid location":2,"win_percentage_for_player_X":1.7976931348623157E308},"f38a1db9a82ede27443d5047f491e0b7e034650d130813f2f1f9d47c5ae9dea7":{"win_percentage_for_player_O":5.992310449541053E307,"tie_percentage":5.992310449541053E307,"Priority":false,"Randomly chosen grid location":6,"win_percentage_for_player_X":5.992310449541053E307}},"tie_percentage":null,"MAX tie_percentage":1.7976931348623157E308,"r1c1":"_","r1c2":"_","r2c1":"O","BEST child O":8,"r1c3":"_","r2c2":"X","r3c1":"O","BEST child tie":8,"win_percentage_for_player_O":null,"Randomly chosen grid location":7,"MAX win_percentage_for_player_X":1.7976931348623157E308,"WORST child X":8,"Children Amount":4,"MAX win_percentage_for_player_O":1.7976931348623157E308,"stateOccurenceCounter":11,"MIN tie_percentage":0.0,"win_percentage_for_player_X":null,"WORST child O":8,"MIN win_percentage_for_player_O":0.0}