{"MIN win_percentage_for_player_X":0.0,"r2c3":"X","r3c2":"_","r3c3":"X","Grid":"O,_,O\nX,O,X\nX,_,X","BEST child X":0,"WORST child tie":2,"children":{"500e727c1d1506876cdab79ae17bd8badeef9f469540749d8717dfd976f624d8":{"win_percentage_for_player_O":100.0,"tie_percentage":0.0,"Priority":false,"Randomly chosen grid location":2,"win_percentage_for_player_X":0.0},"108a93b75314f3ce079a4111884a7befaccf82a173aef151e1d290667fdfc3f1":{"win_percentage_for_player_O":0.0,"tie_percentage":100.0,"Priority":false,"Randomly chosen grid location":8,"win_percentage_for_player_X":0.0}},"tie_percentage":50.0,"MAX tie_percentage":100.0,"r1c1":"O","r1c2":"_","r2c1":"X","BEST child O":2,"r1c3":"O","r2c2":"O","r3c1":"X","BEST child tie":8,"win_percentage_for_player_O":50.0,"Randomly chosen grid location":4,"MAX win_percentage_for_player_X":0.0,"WORST child X":2,"Children Amount":2,"MAX win_percentage_for_player_O":100.0,"stateOccurenceCounter":5,"MIN tie_percentage":0.0,"win_percentage_for_player_X":0.0,"WORST child O":8,"MIN win_percentage_for_player_O":0.0}