{"MIN win_percentage_for_player_X":10.0,"r2c3":"_","r3c2":"_","r3c3":"O","Grid":"O,_,_\nX,X,_\nX,_,O","BEST child X":8,"WORST child tie":8,"children":{"8953d8ceb0bbea61e7261b5ede2afea7e103ee6458e778b61b32f6ee39acc983":{"win_percentage_for_player_O":0.0,"tie_percentage":0.0,"Priority":false,"Randomly chosen grid location":8,"win_percentage_for_player_X":100.0},"92bae0ab8b995ff32980959d52225f6287586ee664215d624ce6c057fb9f4957":{"win_percentage_for_player_O":50.0,"tie_percentage":0.0,"Priority":false,"Randomly chosen grid location":3,"win_percentage_for_player_X":50.0},"9a99702f8dbeaa3c522316401ace3a357efb8a42caeb0f140202ab921badce81":{"win_percentage_for_player_O":16.666666666666668,"tie_percentage":0.0,"Priority":false,"Randomly chosen grid location":6,"win_percentage_for_player_X":83.33333333333333},"36d0cef9ff4a54ab62be6bd8b48694b162dde885b0faa810c6c3ae0623f3c237":{"win_percentage_for_player_O":16.666666666666668,"tie_percentage":0.0,"Priority":false,"Randomly chosen grid location":2,"win_percentage_for_player_X":50.0}},"tie_percentage":0.0,"MAX tie_percentage":0.0,"r1c1":"O","r1c2":"_","r2c1":"X","BEST child O":3,"r1c3":"_","r2c2":"X","r3c1":"X","BEST child tie":0,"win_percentage_for_player_O":20.833333333333336,"Randomly chosen grid location":4,"MAX win_percentage_for_player_X":100.0,"WORST child X":0,"Children Amount":4,"MAX win_percentage_for_player_O":50.0,"stateOccurenceCounter":31,"MIN tie_percentage":0.0,"win_percentage_for_player_X":70.83333333333333,"WORST child O":8,"MIN win_percentage_for_player_O":0.0}