{"MIN win_percentage_for_player_X":0.0,"r2c3":"X","r3c2":"_","r3c3":"_","Grid":"_,_,O\nX,O,X\nX,_,_","BEST child X":9,"WORST child tie":9,"children":{"6bac16deec7ec7db5b8ffd0da6965ab081d6b682ab02a50b0ac810c8f4100d29":{"win_percentage_for_player_O":33.333333333333336,"tie_percentage":0.0,"Priority":false,"Randomly chosen grid location":9,"win_percentage_for_player_X":66.66666666666667},"e1e9729ef45660c26d911a16c9b1cbbefa329644fa7cf30fc76557ebacfe2051":{"win_percentage_for_player_O":25.0,"tie_percentage":25.0,"Priority":false,"Randomly chosen grid location":1,"win_percentage_for_player_X":0.0},"1873a8e1979e7ec40ab78007820a51806a30a62c791aa7cf584887284a1afc6a":{"win_percentage_for_player_O":16.666666666666668,"tie_percentage":33.333333333333336,"Priority":false,"Randomly chosen grid location":8,"win_percentage_for_player_X":50.0}},"tie_percentage":19.444444444444446,"MAX tie_percentage":33.333333333333336,"r1c1":"_","r1c2":"_","r2c1":"X","BEST child O":9,"r1c3":"O","r2c2":"O","r3c1":"X","BEST child tie":8,"win_percentage_for_player_O":25.0,"Randomly chosen grid location":6,"MAX win_percentage_for_player_X":66.66666666666667,"WORST child X":1,"Children Amount":3,"MAX win_percentage_for_player_O":33.333333333333336,"stateOccurenceCounter":9,"MIN tie_percentage":0.0,"win_percentage_for_player_X":38.88888888888889,"WORST child O":0,"MIN win_percentage_for_player_O":10.0}