{"MIN win_percentage_for_player_X":0.0,"r2c3":"O","r3c2":"_","r3c3":"_","Grid":"_,X,_\n_,O,O\nX,_,_","BEST child X":4,"WORST child tie":1,"children":{"dfe63e178772bfc9b6c0e21de6ff07c04d34d8a99510cd6d78ae5d6b72252fe3":{"win_percentage_for_player_O":72.22222222222223,"tie_percentage":27.777777777777782,"Priority":false,"Randomly chosen grid location":3,"win_percentage_for_player_X":0.0},"97978022cda6d1ad4c821c4536f2add884e0bec4083fbe9c7fc9b68f68ac9fc6":{"win_percentage_for_player_O":0.0,"tie_percentage":0.0,"Priority":false,"Randomly chosen grid location":1,"win_percentage_for_player_X":0.0},"501a5540c5f7f62735be93ed4dd4edf575b70a0b5f772aa194824c0c66600be1":{"win_percentage_for_player_O":50.0,"tie_percentage":0.0,"Priority":false,"Randomly chosen grid location":8,"win_percentage_for_player_X":12.5},"9c1c8e3f93f7ec00be66a3f26602d79be169d7f2afe54c67585021d9d2bd02f2":{"win_percentage_for_player_O":33.333333333333336,"tie_percentage":33.333333333333336,"Priority":false,"Randomly chosen grid location":9,"win_percentage_for_player_X":33.33333333333333},"7e41844a75d071d6b7f85f32dbf1b7329d936e7c04816534b65e2fc9989411bb":{"win_percentage_for_player_O":18.75,"tie_percentage":20.833333333333336,"Priority":false,"Randomly chosen grid location":4,"win_percentage_for_player_X":60.41666666666667}},"tie_percentage":16.388888888888893,"MAX tie_percentage":33.333333333333336,"r1c1":"_","r1c2":"X","r2c1":"_","BEST child O":3,"r1c3":"_","r2c2":"O","r3c1":"X","BEST child tie":9,"win_percentage_for_player_O":34.861111111111114,"Randomly chosen grid location":5,"MAX win_percentage_for_player_X":60.41666666666667,"WORST child X":3,"Children Amount":5,"MAX win_percentage_for_player_O":72.22222222222223,"stateOccurenceCounter":40,"MIN tie_percentage":0.0,"win_percentage_for_player_X":21.25,"WORST child O":1,"MIN win_percentage_for_player_O":0.0}