{"MIN win_percentage_for_player_X":10.0,"r2c3":"O","r3c2":"X","r3c3":"O","Grid":"_,O,X\nX,_,O\n_,X,O","BEST child X":7,"WORST child tie":7,"children":{"d2b0740edb7418fb767a2b690bc9f7b1b8c243aad8e7944ad189621dd1be8e72":{"win_percentage_for_player_O":0.0,"tie_percentage":0.0,"Priority":false,"Randomly chosen grid location":7,"win_percentage_for_player_X":100.0},"55cd5b4c140a00606955878068544934253e021737e60ac0847061d724c4b38e":{"win_percentage_for_player_O":0.0,"tie_percentage":0.0,"Priority":false,"Randomly chosen grid location":1,"win_percentage_for_player_X":100.0},"9c9dbe5398cb036baad177b9f5d4ef77767a46072b2f754bc209671482872226":{"win_percentage_for_player_O":0.0,"tie_percentage":50.0,"Priority":false,"Randomly chosen grid location":5,"win_percentage_for_player_X":50.0}},"tie_percentage":16.666666666666668,"MAX tie_percentage":50.0,"r1c1":"_","r1c2":"O","r2c1":"X","BEST child O":0,"r1c3":"X","r2c2":"_","r3c1":"_","BEST child tie":5,"win_percentage_for_player_O":0.0,"Randomly chosen grid location":2,"MAX win_percentage_for_player_X":100.0,"WORST child X":0,"Children Amount":3,"MAX win_percentage_for_player_O":0.0,"stateOccurenceCounter":12,"MIN tie_percentage":0.0,"win_percentage_for_player_X":83.33333333333333,"WORST child O":7,"MIN win_percentage_for_player_O":0.0}