{"MIN win_percentage_for_player_X":10.0,"r2c3":"O","r3c2":"_","r3c3":"_","Grid":"_,X,X\n_,X,O\nO,_,_","BEST child X":8,"WORST child tie":4,"children":{"35ef5aac2ec9f5b0e8cabeed378b54d4688b991487a74c6d0702fed485bb889e":{"win_percentage_for_player_O":0.0,"tie_percentage":0.0,"Priority":false,"Randomly chosen grid location":4,"win_percentage_for_player_X":66.66666666666667},"90b782a969eed40cd9a9aaf2086041d17b217474e1514e0cb63953dc286f2403":{"win_percentage_for_player_O":16.666666666666668,"tie_percentage":33.333333333333336,"Priority":false,"Randomly chosen grid location":1,"win_percentage_for_player_X":16.666666666666668},"99a70d34e6bd2ebc297a4514fc66fa39bbb85eddbbffe9c97a7d3f10dae700d5":{"win_percentage_for_player_O":16.666666666666668,"tie_percentage":0.0,"Priority":false,"Randomly chosen grid location":9,"win_percentage_for_player_X":50.0},"a325da0d5d5413ee17e87b99e275a3cb93cf1452dc8d4b304a39410402ee7fc8":{"win_percentage_for_player_O":5.992310449541053E307,"tie_percentage":5.992310449541053E307,"Priority":false,"Randomly chosen grid location":8,"win_percentage_for_player_X":5.992310449541053E307}},"tie_percentage":1.4980776123852632E307,"MAX tie_percentage":5.992310449541053E307,"r1c1":"_","r1c2":"X","r2c1":"_","BEST child O":8,"r1c3":"X","r2c2":"X","r3c1":"O","BEST child tie":8,"win_percentage_for_player_O":1.4980776123852632E307,"Randomly chosen grid location":2,"MAX win_percentage_for_player_X":5.992310449541053E307,"WORST child X":0,"Children Amount":4,"MAX win_percentage_for_player_O":5.992310449541053E307,"stateOccurenceCounter":18,"MIN tie_percentage":0.0,"win_percentage_for_player_X":1.4980776123852632E307,"WORST child O":4,"MIN win_percentage_for_player_O":0.0}